teili/__init__.py
teili/building_blocks/__init__.py
teili/building_blocks/building_block.py
teili/building_blocks/chain.py
teili/building_blocks/octa.py
teili/building_blocks/reservoir.py
teili/building_blocks/sequence_learning.py
teili/building_blocks/threeway.py
teili/building_blocks/wta.py
teili/core/__init__.py
teili/core/groups.py
teili/core/network.py
teili/core/tags.py
teili/models/__init__.py
teili/models/neuron_models.py
teili/models/synapse_models.py
teili/models/builder/__init__.py
teili/models/builder/combine.py
teili/models/builder/neuron_equation_builder.py
teili/models/builder/synapse_equation_builder.py
teili/models/builder/templates/__init__.py
teili/models/builder/templates/neuron_templates.py
teili/models/builder/templates/synapse_templates.py
teili/models/equations/__init__.py
teili/models/parameters/__init__.py
teili/models/parameters/constants.py
teili/models/parameters/dpi_neuron_param.py
teili/models/parameters/dpi_shunting_synapse_param.py
teili/models/parameters/dpi_synapse_param.py
teili/models/parameters/exp_adapt_if_param.py
teili/models/parameters/exp_chip_stdp_syn_param.py
teili/models/parameters/exp_lif_param.py
teili/models/parameters/exp_syn_param.py
teili/models/parameters/izhikevich_param.py
teili/models/parameters/lif_chip_param.py
teili/models/parameters/linear_lif_param.py
teili/models/parameters/no_mismatch_parameters.py
teili/models/parameters/octa_params.py
teili/stimuli/__init__.py
teili/stimuli/testbench.py
teili/tools/__init__.py
teili/tools/add_run_reg.py
teili/tools/bb_tools.py
teili/tools/converter.py
teili/tools/cpptools.py
teili/tools/distance.py
teili/tools/generate_teiliApps.py
teili/tools/group_tools.py
teili/tools/indexing.py
teili/tools/io.py
teili/tools/live.py
teili/tools/misc.py
teili/tools/parallelization.py
teili/tools/plotter2d.py
teili/tools/plotting.py
teili/tools/prob_distributions.py
teili/tools/random_sampling.py
teili/tools/random_walk.py
teili/tools/run_reg_functions.py
teili/tools/sorting.py
teili-1.1.0.dist-info/LICENSE
teili-1.1.0.dist-info/METADATA
teili-1.1.0.dist-info/WHEEL
teili-1.1.0.dist-info/top_level.txt
teili-1.1.0.dist-info/RECORD
