Metadata-Version: 2.1
Name: teili
Version: 1.1.0
Summary: This toolbox was developed to provide computational  neuroscientists and neuromorphic engineers with a playground for implementing neural algorithms which are simulated using Brian 2.
Home-page: https://code.ini.uzh.ch/ncs/teili
Author: Moritz B. Milde
Author-email: m.milde@westernsydney.edu.au
License: MIT
Keywords: Neural algorithms,building blocks,Spiking Neural Networks
Platform: UNKNOWN
Classifier: Development Status :: 5 - Production/Stable
Classifier: License :: OSI Approved :: MIT License
Classifier: Intended Audience :: Science/Research
Classifier: Operating System :: MacOS :: MacOS X
Classifier: Operating System :: Microsoft :: Windows
Classifier: Operating System :: POSIX
Classifier: Programming Language :: Python :: 3
Classifier: Programming Language :: Python :: 3.7
Requires-Dist: setuptools (>=39.2.0)
Requires-Dist: numpy (>=1.15.1)
Requires-Dist: seaborn (>=0.8.1)
Requires-Dist: sparse (>=0.3.0)
Requires-Dist: Brian2 (==2.2.2.1)
Requires-Dist: scipy (>=1.1.0)
Requires-Dist: pyqtgraph (>=0.10.0)
Requires-Dist: pandas (>=0.23.1)
Requires-Dist: matplotlib (>=2.2.2)
Requires-Dist: h5py (>=2.8.0)
Requires-Dist: pyqt5 (>=5.10.1)
Requires-Dist: sympy (==1.5.1)
